hawkflowairflow/__init__.py
hawkflowairflow/hawkflow_callbacks.py
hawkflowairflow-0.0.3.dist-info/LICENSE
hawkflowairflow-0.0.3.dist-info/METADATA
hawkflowairflow-0.0.3.dist-info/WHEEL
hawkflowairflow-0.0.3.dist-info/top_level.txt
hawkflowairflow-0.0.3.dist-info/RECORD
